constants/__init__.py
constants/functions.py
constants/main.py
constants/values.py
constantsbyyuvneil-1.0.5.dist-info/METADATA
constantsbyyuvneil-1.0.5.dist-info/WHEEL
constantsbyyuvneil-1.0.5.dist-info/top_level.txt
constantsbyyuvneil-1.0.5.dist-info/RECORD
