Metadata-Version: 2.4
Name: ConstantsByYuvneil
Version: 1.0.5
Summary: A simple Python package for scientific and mathematical constants.
Author-email: __Yuneil__ <yuvneiledu44@gmail.com>
Project-URL: Homepage, https://github.com/your-username/my-constants-yourusername
Project-URL: Issues, https://github.com/your-username/my-constants-yourusername/issues
Classifier: Programming Language :: Python :: 3
Classifier: License :: OSI Approved :: MIT License
Classifier: Operating System :: OS Independent
Requires-Python: >=3.8
